rustytorch-0.1.0.dist-info/METADATA
rustytorch-0.1.0.dist-info/WHEEL
tinytorch/__init__.py
tinytorch/tinytorch.cpython-312-darwin.so
rustytorch-0.1.0.dist-info/RECORD
